README.md
treesumstats/__init__.py
treesumstats/balance_sumstats.py
treesumstats/basic_sumstats.py
treesumstats/branch_sumstats.py
treesumstats/calculator.py
treesumstats/event_time_sumstats.py
treesumstats/help.py
treesumstats/ltt_sumstats.py
treesumstats/resolution_sumstats.py
treesumstats/subtree_sumstats.py
treesumstats/sumstats.py
treesumstats/transmission_chain_sumstats.py
treesumstats/tree_manager.py
treesumstats-0.7.dist-info/LICENSE
treesumstats-0.7.dist-info/METADATA
treesumstats-0.7.dist-info/WHEEL
treesumstats-0.7.dist-info/entry_points.txt
treesumstats-0.7.dist-info/top_level.txt
treesumstats-0.7.dist-info/RECORD
