Metadata-Version: 2.1
Name: treesumstats
Version: 0.7
Summary: Encoding phylogenetic trees with summary statistics.
Home-page: https://github.com/evolbioinfo/treesumstats
Author: Anna Zhukova
Author-email: anna.zhukova@pasteur.fr
Keywords: phylogenetics,summary statistics,phylogenetic trees,phylogeny
Classifier: Development Status :: 4 - Beta
Classifier: Environment :: Console
Classifier: Intended Audience :: Developers
Classifier: Topic :: Scientific/Engineering :: Bio-Informatics
Classifier: Topic :: Software Development
Classifier: Topic :: Software Development :: Libraries :: Python Modules
License-File: LICENSE
Requires-Dist: ete3
Requires-Dist: numpy==2.0.2
Requires-Dist: scipy==1.14.1
Requires-Dist: biopython
Requires-Dist: pandas==2.2.3
